simple_fastcgi/__init__.py
simple_fastcgi/async_handler.py
simple_fastcgi/http_response.py
simple_fastcgi/protocol.py
simple_fastcgi/socket_handler.py
simple_fastcgi-0.0.3.dist-info/licenses/LICENSE
simple_fastcgi-0.0.3.dist-info/METADATA
simple_fastcgi-0.0.3.dist-info/WHEEL
simple_fastcgi-0.0.3.dist-info/top_level.txt
simple_fastcgi-0.0.3.dist-info/RECORD
