Metadata-Version: 2.4
Name: simple-fastcgi
Version: 0.0.3
Summary: simple FastCGI sync/async handler in pure python
Author-email: USN484259 <USN484259@outlook.com>
License-Expression: MIT
Project-URL: Homepage, https://github.com/USN484259/simple-fastcgi
Keywords: fastcgi,fcgi,cgi,http,rfc3875
Classifier: Programming Language :: Python :: 3
Classifier: Programming Language :: Python :: 3.8
Classifier: Programming Language :: Python :: 3.9
Classifier: Programming Language :: Python :: 3.10
Classifier: Programming Language :: Python :: 3.11
Classifier: Programming Language :: Python :: 3.12
Classifier: Programming Language :: Python :: 3.13
Requires-Python: >=3.8
License-File: LICENSE
Dynamic: license-file
